MANIFEST.in
README.md
setup.py
src/sentry_searchbutton/__init__.py
src/sentry_searchbutton/plugin.py
src/sentry_searchbutton.egg-info/PKG-INFO
src/sentry_searchbutton.egg-info/SOURCES.txt
src/sentry_searchbutton.egg-info/dependency_links.txt
src/sentry_searchbutton.egg-info/entry_points.txt
src/sentry_searchbutton.egg-info/not-zip-safe
src/sentry_searchbutton.egg-info/requires.txt
src/sentry_searchbutton.egg-info/top_level.txt
src/sentry_searchbutton/templates/.DS_Store
src/sentry_searchbutton/templates/searchbutton/widget.html