Metadata-Version: 1.1
Name: sentry-searchbutton
Version: 0.1.0
Summary: A Sentry extension that introduces a search button for errors
Home-page: http://github.com/timmyomahony/sentry-seachbutton
Author: Timmy O'Mahony
Author-email: me@timmyomahony.com
License: BSD
Platform: UNKNOWN
Classifier: Framework :: Django
Classifier: Intended Audience :: Developers
Classifier: Intended Audience :: System Administrators
Classifier: Operating System :: OS Independent
Classifier: Topic :: Software Development
